Metadata-Version: 2.1
Name: superstream-py
Version: 1.0.0
Summary: superstream
Author-Email: Memphis.dev team <team@memphis.dev>
License: MIT
Requires-Python: >=3.8
Requires-Dist: pydantic>=2.6.3
Requires-Dist: nats-py>=2.7.2
Requires-Dist: protobuf>=4.25.3
Requires-Dist: asyncio>=3.4.3
Requires-Dist: confluent-kafka>=2.3.0
Requires-Dist: requests>=2.31.0
Requires-Dist: jsonschema>=4.21.1
Requires-Dist: nest-asyncio>=1.6.0
Requires-Dist: pytest>=8.0.2; extra == "pytest"
Requires-Dist: pytest-mock>=3.12.0; extra == "pytest"
Provides-Extra: pytest
